[
    {
        "hostId": "Host 1",
        "hostName": "Jurandir.local",
        "groupsList": [
            "localization",
            "basic"
        ]
    },
    {
        "hostId": "Host 2",
        "hostName": "pitu.local",
        "groupsList": [
            "discovery",
            "basic"
        ]
    },
    {
        "hostId": "Host 3",
        "hostName": "absinto.local",
        "groupsList": [
            "security",
            "basic"
        ]
    },
    {
        "hostId": "Host 4",
        "hostName": "rum.local",
        "groupsList": [
            "composition",
            "basic"
        ]
    },
    {
        "hostId": "Host 5",
        "hostName": "catuaba.local",
        "groupsList": [
            "composition",
            "basic"
        ]
    }
]